use_random_quote/__init__.py
use_random_quote/use_random_quote.py
use_random_quote-0.1.0.dist-info/METADATA
use_random_quote-0.1.0.dist-info/WHEEL
use_random_quote-0.1.0.dist-info/RECORD
